{
    "Name": "RHODA JACKSON",
    "Email": "rhodajackson@email.com",
    "Phone": "123) 456-7890\n",
    "Skills": [
        "Adobe Photoshop",
        "Adobe Illustrator",
        "Adobe After Effects",
        "Adobe InDesign",
        "Adobe Premiere Pro",
        "Facebook",
        "Instagram",
        "TikTok",
        "HTML",
        "CSS",
        "Microsoft Word",
        "PowerPoint",
        "Graphic Design",
        "Video Production",
        "Motion Graphics",
        "Sound Design",
        "UI Design",
        "Branding",
        "Logo Design",
        "Presentation Design",
        "Content Creation",
        "Social Media Management",
        "Web Design",
        "A/B Testing",
        "Team Leadership",
        "Digital Marketing"
    ],
    "Education": [
        "B.F.A."
    ],
    "Experience": [
        "WORK EXPERIENCE",
        "Worked with editorial, product marketing, social, and creative",
        "Organized a cross-functional workshop on the importance of",
        "Implemented an A/B testing framework for digital ads, which"
    ],
    "GPA": "Not Found",
    "Summary": "Rhoda Jackson is an accomplished Graphic Designer with experience at Mozilla, Carta Healthcare, and Emanate, holding a B.F.A. in Visual Arts from the University of Chicago. At Mozilla, she significantly improved ad performance by 19% and content shareability by 57% through the design of marketing video assets and the creation of graphic design standards. Her prior role at Carta Healthcare saw her boost social engagement by 32% and slash cost per acquisition by 18% by developing original graphics and implementing A/B testing. She also gained foundational experience designing for 17 clients and creating visual content that garnered over 1,600 engagement points during her internship.",
    "Score": 40.0
}